schwab_api_wrapper/__init__.py
schwab_api_wrapper/__main__.py
schwab_api_wrapper/base_client.py
schwab_api_wrapper/file_client.py
schwab_api_wrapper/oauth_exception.py
schwab_api_wrapper/proxy_client.py
schwab_api_wrapper/redis_client.py
schwab_api_wrapper/response_aware_retry.py
schwab_api_wrapper/token_authority_client.py
schwab_api_wrapper/token_censor_filter.py
schwab_api_wrapper/utils.py
schwab_api_wrapper/schemas/__init__.py
schwab_api_wrapper/schemas/oauth.py
schwab_api_wrapper/schemas/market_data/__init__.py
schwab_api_wrapper/schemas/market_data/errors_schema.py
schwab_api_wrapper/schemas/market_data/instruments_schemas.py
schwab_api_wrapper/schemas/market_data/market_hours_schemas.py
schwab_api_wrapper/schemas/market_data/price_history_schemas.py
schwab_api_wrapper/schemas/market_data/quotes_schemas.py
schwab_api_wrapper/schemas/trader_api/__init__.py
schwab_api_wrapper/schemas/trader_api/accounts_schemas.py
schwab_api_wrapper/schemas/trader_api/errors_schema.py
schwab_api_wrapper/schemas/trader_api/orders_schemas.py
schwab_api_wrapper/schemas/trader_api/transactions_schemas.py
schwab_api_wrapper-0.3.1.dist-info/licenses/LICENSE
schwab_api_wrapper-0.3.1.dist-info/METADATA
schwab_api_wrapper-0.3.1.dist-info/WHEEL
schwab_api_wrapper-0.3.1.dist-info/top_level.txt
schwab_api_wrapper-0.3.1.dist-info/RECORD
